excelop/__init__.py
excelop/__main__.py
excelop/excelop.py
excelop-0.1.1.dist-info/LICENSE
excelop-0.1.1.dist-info/METADATA
excelop-0.1.1.dist-info/WHEEL
excelop-0.1.1.dist-info/top_level.txt
excelop-0.1.1.dist-info/zip-safe
excelop-0.1.1.dist-info/RECORD
